surfy/__init__.py
surfy/__main__.py
surfy/surfy.py
surfy/sqlite/__init__.py
surfy/sqlite/__main__.py
surfy/sqlite/db.py
surfy/wiki/__init__.py
surfy/wiki/__main__.py
surfy/wiki/main.py
surfy-1.1.1.dist-info/METADATA
surfy-1.1.1.dist-info/WHEEL
surfy-1.1.1.dist-info/top_level.txt
surfy-1.1.1.dist-info/RECORD
