Metadata-Version: 2.1
Name: surfy
Version: 1.1.1
Summary: This repository contains all the libraries for successful working with Surfy Ecosystem in a Python environment.
Author: Alexander Yermolenko, PugoBoss, Eugen Nukatak
Project-URL: Homepage, https://surfy.one
Project-URL: GitHub, https://github.com/surfy-one/core.py
Project-URL: Bug Tracker, https://github.com/surfy-one/core.py/issues
Keywords: surfy,sqlite
Classifier: Programming Language :: Python :: 3
Classifier: License :: OSI Approved :: MIT License
Classifier: Operating System :: OS Independent
Requires-Python: >=3.7
